myenigma/__init__.py
myenigma/enigma.py
myenigma/part/__init__.py
myenigma/part/plugboard.py
myenigma/part/plate/__init__.py
myenigma/part/plate/entry_plate.py
myenigma/part/plate/plate.py
myenigma/part/plate/reflector.py
myenigma/part/plate/rotor.py
myenigma/sample_plate/__init__.py
myenigma/sample_plate/reflector.py
myenigma/sample_plate/rotor.py
myenigma-2.0.2.dist-info/LICENSE
myenigma-2.0.2.dist-info/METADATA
myenigma-2.0.2.dist-info/WHEEL
myenigma-2.0.2.dist-info/top_level.txt
myenigma-2.0.2.dist-info/RECORD
