Metadata-Version: 2.1
Name: myenigma
Version: 2.0.2
Summary: Python-based Enigma.
Home-page: https://github.com/DingJunyao/myenigma
Author: DingJunyao
Author-email: dingjunyao0703@163.com
License: UNKNOWN
Project-URL: Source, https://github.com/DingJunyao/myenigma
Project-URL: Bug Tracker, https://github.com/DingJunyao/myenigma/issues
Platform: UNKNOWN
Classifier: Programming Language :: Python :: 3
Classifier: License :: OSI Approved :: MIT License
Classifier: Operating System :: OS Independent
Classifier: Topic :: Security :: Cryptography
Classifier: Topic :: Sociology :: History
Classifier: Topic :: Education
Classifier: Topic :: Utilities
Requires-Python: >=3.10
License-File: LICENSE
